logmerger/__init__.py
logmerger/__main__.py
logmerger/about.py
logmerger/demo.py
logmerger/file_reading.py
logmerger/interactive_viewing.py
logmerger/logmerger.py
logmerger/merging.py
logmerger/multiline_log_handler.py
logmerger/timestamp_wrapper.py
logmerger/tui/__init__.py
logmerger/tui/dialogs.py
logmerger/tui/validators.py
log_merger-0.5.0.dist-info/LICENSE
log_merger-0.5.0.dist-info/METADATA
log_merger-0.5.0.dist-info/WHEEL
log_merger-0.5.0.dist-info/entry_points.txt
log_merger-0.5.0.dist-info/top_level.txt
log_merger-0.5.0.dist-info/RECORD
