Metadata-Version: 2.1
Name: log-merger
Version: 0.5.0
Summary: A command-line utility to display multiple log files, merged by log timestamp
Author: Paul McGuire
Author-email: ptmcg.pm@gmail.com
Project-URL: Source, https://github.com/ptmcg/logmerger
Classifier: Development Status :: 3 - Alpha
Classifier: Environment :: Console
Classifier: Intended Audience :: Developers
Classifier: Intended Audience :: Information Technology
Classifier: Intended Audience :: System Administrators
Classifier: License :: OSI Approved :: MIT License
Classifier: Operating System :: OS Independent
Classifier: Programming Language :: Python :: 3
Classifier: Programming Language :: Python :: 3 :: Only
Classifier: Programming Language :: Python :: 3.9
Classifier: Programming Language :: Python :: 3.10
Classifier: Programming Language :: Python :: 3.11
Classifier: Programming Language :: Python :: 3.12
Classifier: Topic :: System :: Systems Administration
Classifier: Topic :: Utilities
Classifier: Typing :: Typed
Requires-Python: >=3.9
License-File: LICENSE
Requires-Dist: littletable
Requires-Dist: rich
Requires-Dist: textual
Provides-Extra: pcap
Requires-Dist: pyshark ; extra == 'pcap'
